{
  "book_id_title": "6186357-the-maze-runner",
  "book_id": "6186357",
  "book_title": "The Maze Runner",
  "book_description": "There are alternate cover editions for this ASIN here and here.If you ain\u2019t scared, you ain\u2019t human. When Thomas wakes up in the lift, the only thing he can remember is his name. He\u2019s surrounded by strangers\u2014boys whose memories are also gone. Nice to meet ya, shank. Welcome to the Glade. Outside the towering stone walls that surround the Glade is a limitless, ever-changing maze. It\u2019s the only way out\u2014and no one\u2019s ever made it through alive. Everything is going to change. Then a girl arrives. The first girl ever. And the message she delivers is terrifying. Remember. Survive. Run.",
  "book_url": "https://www.goodreads.com/book/show/6186357-the-maze-runner",
  "book_image": "https://images-na.ssl-images-amazon.com/images/S/compressed.photo.goodreads.com/books/1375596592i/6186357.jpg",
  "book_series_uri": "https://www.goodreads.com/series/110451-the-maze-runner",
  "year_first_published": "2009",
  "num_pages": 384,
  "genres": [
    "Young Adult",
    "Dystopia",
    "Science Fiction",
    "Fiction",
    "Fantasy",
    "Audiobook",
    "Post Apocalyptic"
  ],
  "num_ratings": 1583168,
  "num_reviews": 67587,
  "average_rating": 4.05,
  "author": {
    "author_id_title": "348878.James_Dashner",
    "author_id": "348878",
    "author_name": "James Dashner",
    "author_url": "https://www.goodreads.com/author/show/348878.James_Dashner",
    "author_image": "https://images.gr-assets.com/authors/1473791260p5/348878.jpg",
    "author_description": null
  },
  "rating": 2,
  "dates_read": [],
  "shelves": [
    "read"
  ]
}